barbarum_orm/__init__.py
barbarum_orm/common/__init__.py
barbarum_orm/common/database.py
barbarum_orm/common/repository.py
barbarum_orm/common/dialect/__init__.py
barbarum_orm/common/dialect/dialect.py
barbarum_orm/common/dialect/mysql_dialect.py
barbarum_orm/utils/__init__.py
barbarum_orm/utils/app_logger.py
barbarum_orm-0.1.1.dist-info/LICENSE
barbarum_orm-0.1.1.dist-info/METADATA
barbarum_orm-0.1.1.dist-info/WHEEL
barbarum_orm-0.1.1.dist-info/top_level.txt
barbarum_orm-0.1.1.dist-info/RECORD
